pytest_skip/__init__.py
pytest_skip/plugin.py
pytest_skip-0.2.0.dist-info/licenses/LICENSE
pytest_skip-0.2.0.dist-info/METADATA
pytest_skip-0.2.0.dist-info/WHEEL
pytest_skip-0.2.0.dist-info/entry_points.txt
pytest_skip-0.2.0.dist-info/top_level.txt
pytest_skip-0.2.0.dist-info/RECORD
